poledni_menu/__init__.py
poledni_menu/digest.py
poledni_menu/email_menu.py
poledni_menu/generate.py
poledni_menu/isholiday.py
poledni_menu/utils.py
poledni_menu/version.py
poledni_menu/extractors/__init__.py
poledni_menu/extractors/agata.py
poledni_menu/extractors/avantgardino.py
poledni_menu/extractors/bernard_pub.py
poledni_menu/extractors/blox.py
poledni_menu/extractors/budvarka.py
poledni_menu/extractors/kulatak.py
poledni_menu/extractors/nakotlarce.py
poledni_menu/extractors/obedar.py
poledni_menu/extractors/potrefena_husa.py
poledni_menu/extractors/potrefene_husy.py
poledni_menu/extractors/zomato.py
poledni_menu-0.15.dist-info/LICENSE
poledni_menu-0.15.dist-info/METADATA
poledni_menu-0.15.dist-info/WHEEL
poledni_menu-0.15.dist-info/entry_points.txt
poledni_menu-0.15.dist-info/top_level.txt
poledni_menu-0.15.dist-info/RECORD
