Metadata-Version: 2.1
Name: poledni-menu
Version: 0.15
Summary: Scrap daily menu and send it via e-mail
Home-page: https://github.com/oskar456/poledni-menu
Author: Ondřej Caletka
Author-email: ondrej@caletka.cz
License: MIT
Platform: UNKNOWN
Classifier: Development Status :: 3 - Alpha
Classifier: Environment :: Console
Classifier: Intended Audience :: Information Technology
Classifier: License :: OSI Approved :: MIT License
Classifier: Programming Language :: Python :: 3
Classifier: Programming Language :: Python :: 3.6
Classifier: Programming Language :: Python :: 3 :: Only
Classifier: Topic :: Utilities
Requires-Python: >=3.6
Requires-Dist: click
Requires-Dist: lxml
Requires-Dist: pyyaml
Requires-Dist: markdown
